mnl_ws_norm/__init__.py
mnl_ws_norm/normalizer.py
mnl_ws_norm-0.0.4.dist-info/LICENSE.txt
mnl_ws_norm-0.0.4.dist-info/METADATA
mnl_ws_norm-0.0.4.dist-info/WHEEL
mnl_ws_norm-0.0.4.dist-info/top_level.txt
mnl_ws_norm-0.0.4.dist-info/RECORD
